looper/__init__.py
looper/looper.py
looper-daemon/__init__.py
looper-daemon/looper.py
looper_daemon-0.13.dist-info/LICENSE
looper_daemon-0.13.dist-info/METADATA
looper_daemon-0.13.dist-info/WHEEL
looper_daemon-0.13.dist-info/top_level.txt
looper_daemon-0.13.dist-info/RECORD
