Metadata-Version: 2.1
Name: looper-daemon
Version: 0.13
Summary: Create a looping function that can be interrupted
Home-page: http://github.com/jacobmsft/looper
Author: Suraj Jacob
Author-email: jacob.suraj@live.com
License: MIT
Platform: UNKNOWN
